aspire/__init__.py
aspire/aspire.py
aspire/history.py
aspire/plot.py
aspire/samples.py
aspire/transforms.py
aspire/utils.py
aspire/flows/__init__.py
aspire/flows/base.py
aspire/flows/jax/__init__.py
aspire/flows/jax/flows.py
aspire/flows/jax/utils.py
aspire/flows/torch/__init__.py
aspire/flows/torch/flows.py
aspire/samplers/__init__.py
aspire/samplers/base.py
aspire/samplers/importance.py
aspire/samplers/mcmc.py
aspire/samplers/smc/__init__.py
aspire/samplers/smc/base.py
aspire/samplers/smc/blackjax.py
aspire/samplers/smc/emcee.py
aspire/samplers/smc/minipcn.py
aspire_inference-0.1.0a12.dist-info/licenses/LICENSE
aspire_inference-0.1.0a12.dist-info/METADATA
aspire_inference-0.1.0a12.dist-info/WHEEL
aspire_inference-0.1.0a12.dist-info/top_level.txt
aspire_inference-0.1.0a12.dist-info/RECORD
